prettyformatter/__init__.py
prettyformatter/_pretty_class.py
prettyformatter/_pretty_dataclass.py
prettyformatter/_prettyformatter.py
prettyformatter-2.0.13.dist-info/LICENSE
prettyformatter-2.0.13.dist-info/METADATA
prettyformatter-2.0.13.dist-info/WHEEL
prettyformatter-2.0.13.dist-info/top_level.txt
prettyformatter-2.0.13.dist-info/RECORD
