Metadata-Version: 2.1
Name: prettyformatter
Version: 2.0.13
Summary: Pretty formatter enables pretty formatting using hanging indents, dataclasses, ellipses, and simple customizability by registering formatters.
License: mit
Project-URL: Bug Tracker, https://github.com/SimpleArt/prettyformatter/issues
Project-URL: Documentation, https://simpleart.github.io/prettyformatter/
Project-URL: Homepage, https://simpleart.github.io/prettyformatter/
Project-URL: Repository, https://github.com/SimpleArt/prettyformatter
Keywords: pretty,print,format,indent,dataclass
Classifier: Topic :: Printing
Classifier: Development Status :: 5 - Production/Stable
Classifier: License :: OSI Approved :: MIT License
Classifier: Programming Language :: Python :: 3.5
Classifier: Programming Language :: Python :: 3.6
Classifier: Programming Language :: Python :: 3.7
Classifier: Programming Language :: Python :: 3.8
Classifier: Programming Language :: Python :: 3.9
Classifier: Programming Language :: Python :: 3.10
Classifier: Programming Language :: Python :: 3.11
Classifier: Programming Language :: Python :: 3.12
Classifier: Operating System :: OS Independent
Classifier: Intended Audience :: Developers
Classifier: Typing :: Typed
Requires-Python: >=3.5
License-File: LICENSE
